calc/__init__.py
calc/calculator.py
dbdisk/__init__.py
dbdisk/db_disk_cache_builder.py
dbdisk/db_disk_factory.py
dbdisk/db_disk_request.py
dbdisk/helper.py
dbdisk/types.py
dbdisk/caches/__init__.py
dbdisk/caches/db_disk_cache.py
dbdisk/caches/db_disk_cache_csv.py
dbdisk/database/__init__.py
dbdisk/database/database_pg_service.py
dbdisk/database/database_service.py
dbdisk/database/database_sybase_service.py
restq/__init__.py
restq/disk_cache.py
restq/http_cached_request.py
restq/http_request.py
src/__init__.py
src/calc/__init__.py
src/calc/calculator.py
src/common/__init__.py
src/common/app_context.py
src/common/base_builder.py
src/common/constants.py
src/common/helper.py
src/common/caches/__init__.py
src/common/caches/disk_cache.py
src/common/caches/disk_cache_csv.py
src/common/caches/disk_cache_type.py
src/common/database/__init__.py
src/common/database/db_oracle_service.py
src/common/database/db_pg_service.py
src/common/database/db_service.py
src/common/database/db_service_factory.py
src/common/database/db_sybase_service.py
src/common/database/db_type.py
src/dbdisk/__init__.py
src/dbdisk/db_disk_bulk_executor.py
src/dbdisk/db_disk_cache_builder.py
src/dbdisk/db_disk_factory.py
src/dbdisk/db_disk_request.py
src/dbdisk/db_disk_request_executer.py
src/dbdisk/db_disk_result.py
src/dbdisk/db_disk_results.py
src/dbdisk/db_request_executer.py
src/dbdisk/dbdisk_executor_type.py
src/dbdisk/types.py
src/dbdisk/caches/__init__.py
src/dbdisk/caches/db_disk_cache.py
src/dbdisk/caches/db_disk_cache_csv.py
src/dbdisk/database/__init__.py
src/dbdisk/database/database_pg_service.py
src/dbdisk/database/database_service.py
src/dbdisk/database/database_sybase_service.py
src/dbdisk/database/db_oracle_service.py
src/dbdisk/database/db_pg_service.py
src/dbdisk/database/db_service.py
src/dbdisk/database/db_service_factory.py
src/dbdisk/database/db_sybase_service.py
src/dbdisk/executors/__init__.py
src/dbdisk/executors/db_disk_bulk_executor.py
omnijp-2.25.0.dist-info/LICENSE
omnijp-2.25.0.dist-info/METADATA
omnijp-2.25.0.dist-info/WHEEL
omnijp-2.25.0.dist-info/entry_points.txt
omnijp-2.25.0.dist-info/top_level.txt
omnijp-2.25.0.dist-info/RECORD
