Metadata-Version: 2.1
Name: omnijp
Version: 2.25.0
Summary: OmniJP is a Python library that provides tools for common tasks in software development
Home-page: https://github.com/jpothanc/omnijp
Author: Jessish Pothancheri
Author-email: jessish.pothancheri@gmail.com
License: MIT
Platform: UNKNOWN
Classifier: Development Status :: 5 - Production/Stable
Classifier: Intended Audience :: Developers
Classifier: License :: OSI Approved :: MIT License
Classifier: Programming Language :: Python :: 3.8
Requires-Python: >=3.8
License-File: LICENSE
Requires-Dist: retry (>=0.9.2)
Requires-Dist: requests (>=2.31.0)
Requires-Dist: pyodbc (>=5.1.0)
Requires-Dist: psycopg2 (>=2.9.9)
Requires-Dist: openai (~=1.30.5)
Requires-Dist: cx-Oracle (~=8.3.0)
Requires-Dist: pymssql (~=2.3.0)
Requires-Dist: pandas (~=2.2.3)
Requires-Dist: numpy (~=2.0.2)
